{
    "Ar36": {
        "error": 0.0002246846098029096,
        "error_type": "SEM",
        "filter_outliers_dict": {
            "filter_outliers": true,
            "iterations": 1,
            "std_devs": 3,
            "use_iqr_filtering": false,
            "use_standard_deviation_filtering": false
        },
        "fit": "linear",
        "fn": 180,
        "include_baseline_error": true,
        "n": 180,
        "outlier_excluded": [],
        "reviewed": true,
        "user_excluded": [],
        "value": 0.008487933211993473
    },
    "Ar37": {
        "error": 0.005247482920692934,
        "error_type": "SEM",
        "filter_outliers_dict": {
            "filter_outliers": true,
            "iterations": 1,
            "std_devs": 3,
            "use_iqr_filtering": false,
            "use_standard_deviation_filtering": false
        },
        "fit": "linear",
        "fn": 180,
        "include_baseline_error": true,
        "n": 180,
        "outlier_excluded": [],
        "reviewed": true,
        "user_excluded": [],
        "value": -0.01558388709644481
    },
    "Ar38": {
        "error": 0.004333327101800829,
        "error_type": "SEM",
        "filter_outliers_dict": {
            "filter_outliers": true,
            "iterations": 1,
            "std_devs": 3,
            "use_iqr_filtering": false,
            "use_standard_deviation_filtering": false
        },
        "fit": "linear",
        "fn": 180,
        "include_baseline_error": true,
        "n": 180,
        "outlier_excluded": [],
        "reviewed": true,
        "user_excluded": [],
        "value": 0.07482756690333775
    },
    "Ar39": {
        "error": 0.009724151541704177,
        "error_type": "SEM",
        "filter_outliers_dict": {
            "filter_outliers": true,
            "iterations": 1,
            "std_devs": 3,
            "use_iqr_filtering": false,
            "use_standard_deviation_filtering": false
        },
        "fit": "linear",
        "fn": 180,
        "include_baseline_error": true,
        "n": 180,
        "outlier_excluded": [],
        "reviewed": true,
        "user_excluded": [],
        "value": 0.08544597734051215
    },
    "Ar40": {
        "error": 0.01763231747053914,
        "error_type": "SEM",
        "filter_outliers_dict": {
            "filter_outliers": true,
            "iterations": 1,
            "std_devs": 3,
            "use_iqr_filtering": false,
            "use_standard_deviation_filtering": false
        },
        "fit": "parabolic",
        "fn": 179,
        "include_baseline_error": true,
        "n": 180,
        "outlier_excluded": [
            69
        ],
        "reviewed": true,
        "user_excluded": [],
        "value": 1.1608490284772497
    },
    "Ar41": {
        "error": 0.02245058493715752,
        "error_type": "SEM",
        "filter_outliers_dict": {
            "filter_outliers": true,
            "iterations": 1,
            "std_devs": 3
        },
        "fit": "average",
        "value": -0.1553823479647065
    }
}