{
    "Ar36": {
        "error": 0.0002729251076043646,
        "error_type": "SEM",
        "filter_outliers_dict": {
            "filter_outliers": true,
            "iterations": 1,
            "std_devs": 3,
            "use_iqr_filtering": false,
            "use_standard_deviation_filtering": false
        },
        "fit": "linear",
        "fn": 180,
        "include_baseline_error": true,
        "n": 180,
        "outlier_excluded": [],
        "reviewed": true,
        "user_excluded": [],
        "value": 0.01347590599644256
    },
    "Ar37": {
        "error": 0.00525177246797542,
        "error_type": "SEM",
        "filter_outliers_dict": {
            "filter_outliers": true,
            "iterations": 1,
            "std_devs": 3,
            "use_iqr_filtering": false,
            "use_standard_deviation_filtering": false
        },
        "fit": "linear",
        "fn": 180,
        "include_baseline_error": true,
        "n": 180,
        "outlier_excluded": [],
        "reviewed": true,
        "user_excluded": [],
        "value": -0.010436277642432178
    },
    "Ar38": {
        "error": 0.004280393003693065,
        "error_type": "SEM",
        "filter_outliers_dict": {
            "filter_outliers": true,
            "iterations": 1,
            "std_devs": 3,
            "use_iqr_filtering": false,
            "use_standard_deviation_filtering": false
        },
        "fit": "linear",
        "fn": 179,
        "include_baseline_error": true,
        "n": 180,
        "outlier_excluded": [
            153
        ],
        "reviewed": true,
        "user_excluded": [],
        "value": 0.06673596968270229
    },
    "Ar39": {
        "error": 0.020647504966784778,
        "error_type": "SEM",
        "filter_outliers_dict": {
            "filter_outliers": true,
            "iterations": 1,
            "std_devs": 3,
            "use_iqr_filtering": false,
            "use_standard_deviation_filtering": false
        },
        "fit": "parabolic",
        "fn": 180,
        "include_baseline_error": true,
        "n": 180,
        "outlier_excluded": [],
        "reviewed": true,
        "user_excluded": [],
        "value": -0.0025337794136046417
    },
    "Ar40": {
        "error": 0.017974650808088858,
        "error_type": "SEM",
        "filter_outliers_dict": {
            "filter_outliers": true,
            "iterations": 1,
            "std_devs": 3,
            "use_iqr_filtering": false,
            "use_standard_deviation_filtering": false
        },
        "fit": "parabolic",
        "fn": 180,
        "include_baseline_error": true,
        "n": 180,
        "outlier_excluded": [],
        "reviewed": true,
        "user_excluded": [],
        "value": 2.8807166106610076
    },
    "Ar41": {
        "error": 0.021289247841524944,
        "error_type": "SEM",
        "filter_outliers_dict": {
            "filter_outliers": true,
            "iterations": 1,
            "std_devs": 3
        },
        "fit": "average",
        "value": -0.21091804760785998
    }
}