{
    "Ar36": {
        "error": 0.00027531452477575613,
        "error_type": "SEM",
        "filter_outliers_dict": {
            "filter_outliers": true,
            "iterations": 1,
            "std_devs": 3,
            "use_iqr_filtering": false,
            "use_standard_deviation_filtering": false
        },
        "fit": "linear",
        "fn": 179,
        "include_baseline_error": true,
        "n": 180,
        "outlier_excluded": [
            119
        ],
        "reviewed": true,
        "user_excluded": [],
        "value": 0.012037838545206254
    },
    "Ar37": {
        "error": 0.004798542662396567,
        "error_type": "SEM",
        "filter_outliers_dict": {
            "filter_outliers": true,
            "iterations": 1,
            "std_devs": 3,
            "use_iqr_filtering": false,
            "use_standard_deviation_filtering": false
        },
        "fit": "linear",
        "fn": 179,
        "include_baseline_error": true,
        "n": 180,
        "outlier_excluded": [
            28
        ],
        "reviewed": true,
        "user_excluded": [],
        "value": -0.008463959102676388
    },
    "Ar38": {
        "error": 0.004102929162333457,
        "error_type": "SEM",
        "filter_outliers_dict": {
            "filter_outliers": true,
            "iterations": 1,
            "std_devs": 3,
            "use_iqr_filtering": false,
            "use_standard_deviation_filtering": false
        },
        "fit": "linear",
        "fn": 179,
        "include_baseline_error": true,
        "n": 180,
        "outlier_excluded": [
            116
        ],
        "reviewed": true,
        "user_excluded": [],
        "value": 0.09013916346265033
    },
    "Ar39": {
        "error": 0.009733218356430595,
        "error_type": "SEM",
        "filter_outliers_dict": {
            "filter_outliers": true,
            "iterations": 1,
            "std_devs": 3,
            "use_iqr_filtering": false,
            "use_standard_deviation_filtering": false
        },
        "fit": "linear",
        "fn": 180,
        "include_baseline_error": true,
        "n": 180,
        "outlier_excluded": [],
        "reviewed": true,
        "user_excluded": [],
        "value": 0.09124767234588632
    },
    "Ar40": {
        "error": 0.017099767423162594,
        "error_type": "SEM",
        "filter_outliers_dict": {
            "filter_outliers": true,
            "iterations": 1,
            "std_devs": 3,
            "use_iqr_filtering": false,
            "use_standard_deviation_filtering": false
        },
        "fit": "parabolic",
        "fn": 180,
        "include_baseline_error": true,
        "n": 180,
        "outlier_excluded": [],
        "reviewed": true,
        "user_excluded": [],
        "value": 2.5646250368256807
    },
    "Ar41": {
        "error": 0.0220127697459206,
        "error_type": "SEM",
        "filter_outliers_dict": {
            "filter_outliers": true,
            "iterations": 1,
            "std_devs": 3
        },
        "fit": "average",
        "value": -0.1432380697919768
    }
}